setup.py
pbraw/__init__.py
pbraw/dispatcher.py
pbraw/main.py
pbraw/util.py
pbraw.egg-info/PKG-INFO
pbraw.egg-info/SOURCES.txt
pbraw.egg-info/dependency_links.txt
pbraw.egg-info/entry_points.txt
pbraw.egg-info/requires.txt
pbraw.egg-info/top_level.txt
pbraw/handlers/__init__.py
pbraw/handlers/links.py
pbraw/handlers/plain.py
pbraw/handlers/ubuntu.py
pbraw/handlers/url.py