Metadata-Version: 1.0
Name: pbraw
Version: 0.1.2
Summary: A library to extract plaintexts from pastebins
Home-page: https://github.com/Hummer12007/pbraw
Author: Mykyta Holubakha
Author-email: hilobakho@gmail.com
License: MIT
Platform: UNKNOWN
